pytest_semantic_assert/__init__.py
pytest_semantic_assert/assertions.py
pytest_semantic_assert/async_assertions.py
pytest_semantic_assert/cache.py
pytest_semantic_assert/config.py
pytest_semantic_assert/embeddings.py
pytest_semantic_assert/exceptions.py
pytest_semantic_assert/plugin.py
pytest_semantic_assert/similarity.py
pytest_semantic_assert-0.1.5.dist-info/licenses/LICENSE
pytest_semantic_assert-0.1.5.dist-info/METADATA
pytest_semantic_assert-0.1.5.dist-info/WHEEL
pytest_semantic_assert-0.1.5.dist-info/entry_points.txt
pytest_semantic_assert-0.1.5.dist-info/top_level.txt
pytest_semantic_assert-0.1.5.dist-info/RECORD
