Metadata-Version: 2.4
Name: pytest-semantic-assert
Version: 0.1.5
Summary: Pytest plugin for semantic LLM output assertions using embeddings. Test meaning, not strings.
Author-email: pytest-semantic-assert Contributors <pytest-semantic-assert@example.com>
Maintainer-email: pytest-semantic-assert Contributors <pytest-semantic-assert@example.com>
License: MIT
Project-URL: Homepage, https://github.com/pytest-semantic-assert/pytest-semantic-assert
Project-URL: Documentation, https://pytest-semantic-assert.readthedocs.io
Project-URL: Repository, https://github.com/pytest-semantic-assert/pytest-semantic-assert
Project-URL: Bug Tracker, https://github.com/pytest-semantic-assert/pytest-semantic-assert/issues
Keywords: pytest,testing,LLM,semantic,assertions,embeddings,ai,machine-learning
Classifier: Development Status :: 3 - Alpha
Classifier: Framework :: Pytest
Classifier: Intended Audience :: Developers
Classifier: License :: OSI Approved :: MIT License
Classifier: Operating System :: OS Independent
Classifier: Programming Language :: Python :: 3
Classifier: Programming Language :: Python :: 3.9
Classifier: Programming Language :: Python :: 3.10
Classifier: Programming Language :: Python :: 3.11
Classifier: Programming Language :: Python :: 3.12
Classifier: Topic :: Software Development :: Testing
Classifier: Topic :: Software Development :: Quality Assurance
Requires-Python: >=3.9
License-File: LICENSE
Requires-Dist: pytest>=7.0.0
Requires-Dist: sentence-transformers>=2.0.0
Requires-Dist: numpy<2.0.0,>=1.20.0
Requires-Dist: filelock>=3.0.0
Provides-Extra: dev
Requires-Dist: black>=23.0.0; extra == "dev"
Requires-Dist: ruff>=0.1.0; extra == "dev"
Requires-Dist: mypy>=1.0.0; extra == "dev"
Requires-Dist: pytest-cov>=4.0.0; extra == "dev"
Requires-Dist: pytest-xdist>=3.0.0; extra == "dev"
Requires-Dist: pytest-asyncio>=0.21.0; extra == "dev"
Requires-Dist: tox>=4.0.0; extra == "dev"
Requires-Dist: build>=0.10.0; extra == "dev"
Requires-Dist: twine>=4.0.0; extra == "dev"
Requires-Dist: sphinx>=6.0.0; extra == "dev"
Dynamic: license-file
